tantra/__init__.py
tantra/agent.py
tantra/context.py
tantra/engine.py
tantra/exceptions.py
tantra/hooks.py
tantra/mcp.py
tantra/py.typed
tantra/rules.py
tantra/tools.py
tantra/types.py
tantra/checkpoints/__init__.py
tantra/checkpoints/base.py
tantra/checkpoints/postgres.py
tantra/evaluation/__init__.py
tantra/evaluation/base.py
tantra/evaluation/deployment.py
tantra/evaluation/matchers.py
tantra/evaluation/suite.py
tantra/intheloop/__init__.py
tantra/intheloop/base.py
tantra/intheloop/registry.py
tantra/intheloop/warden.py
tantra/memory/__init__.py
tantra/memory/base.py
tantra/memory/conversation.py
tantra/memory/postgres.py
tantra/observability/__init__.py
tantra/observability/logging.py
tantra/observability/telemetry.py
tantra/orchestration/__init__.py
tantra/orchestration/base.py
tantra/orchestration/graph.py
tantra/orchestration/parallel.py
tantra/orchestration/pipeline.py
tantra/orchestration/router.py
tantra/orchestration/solo.py
tantra/orchestration/swarm.py
tantra/providers/__init__.py
tantra/providers/anthropic.py
tantra/providers/base.py
tantra/providers/ollama.py
tantra/providers/openai.py
tantra/resilience/__init__.py
tantra/resilience/ratelimit.py
tantra/resilience/retry.py
tantra/retriever/__init__.py
tantra/retriever/base.py
tantra/retriever/inmemory.py
tantra/serve/__init__.py
tantra/serve/app.py
tantra/serve/factory.py
tantra/serve/models.py
tantra-0.1.0.dist-info/METADATA
tantra-0.1.0.dist-info/WHEEL
tantra-0.1.0.dist-info/licenses/LICENSE
tantra-0.1.0.dist-info/RECORD
