Metadata-Version: 2.4
Name: tantra
Version: 0.1.0
Summary: An observable production-ready open-source AI agent framework.
Project-URL: Homepage, https://tantra.run
Project-URL: Documentation, https://tantra-run.github.io/tantra
Project-URL: Repository, https://github.com/tantra-run/tantra-py
Project-URL: Changelog, https://github.com/tantra-run/tantra-py/blob/main/CHANGELOG.md
Project-URL: Issues, https://github.com/tantra-run/tantra-py/issues
Author: Tantra Team
License-Expression: Apache-2.0
License-File: LICENSE
Keywords: agent-framework,agents,ai,multi-agent,orchestration,swarm
Classifier: Development Status :: 3 - Alpha
Classifier: Intended Audience :: Developers
Classifier: License :: OSI Approved :: Apache Software License
Classifier: Programming Language :: Python :: 3
Classifier: Programming Language :: Python :: 3.11
Classifier: Programming Language :: Python :: 3.12
Classifier: Topic :: Scientific/Engineering :: Artificial Intelligence
Requires-Python: >=3.11
Requires-Dist: anthropic>=0.18
Requires-Dist: asyncpg>=0.29
Requires-Dist: fastapi>=0.100
Requires-Dist: httpx>=0.25
Requires-Dist: nest-asyncio>=1.5
Requires-Dist: openai>=1.0
Requires-Dist: opentelemetry-api>=1.20
Requires-Dist: opentelemetry-exporter-otlp>=1.20
Requires-Dist: opentelemetry-sdk>=1.20
Requires-Dist: pydantic>=2.0
Requires-Dist: tiktoken>=0.5.0
Requires-Dist: uvicorn[standard]>=0.20
Provides-Extra: dev
Requires-Dist: pre-commit>=3.0; extra == 'dev'
Requires-Dist: pytest-asyncio>=0.23; extra == 'dev'
Requires-Dist: pytest-cov>=5.0; extra == 'dev'
Requires-Dist: pytest>=8.0; extra == 'dev'
Requires-Dist: ruff>=0.1; extra == 'dev'
Provides-Extra: docs
Requires-Dist: mkdocs-material>=9.0; extra == 'docs'
Requires-Dist: mkdocstrings[python]>=0.24; extra == 'docs'
